yamon/__init__.py
yamon/cli.py
yamon/history.py
yamon/main.py
yamon/api/__init__.py
yamon/api/metrics.py
yamon/api/websocket.py
yamon/collectors/__init__.py
yamon/collectors/apple_api.py
yamon/collectors/collector.py
yamon/collectors/ioreport.py
yamon/collectors/smc.py
yamon/static/index.html
yamon/static/vite.svg
yamon/static/assets/index-Bvf6ejq0.js
yamon/static/assets/index-D-2gIuSL.css
yamon-0.1.2.dist-info/licenses/LICENSE
yamon-0.1.2.dist-info/METADATA
yamon-0.1.2.dist-info/WHEEL
yamon-0.1.2.dist-info/entry_points.txt
yamon-0.1.2.dist-info/top_level.txt
yamon-0.1.2.dist-info/RECORD
