Metadata-Version: 2.4
Name: yamon
Version: 0.1.2
Summary: Visually pleasing, deep system monitoring for macOS
Author: grapeot
License: MIT
Keywords: macos,monitoring,apple-silicon,system-monitor,performance
Classifier: Development Status :: 4 - Beta
Classifier: Intended Audience :: Developers
Classifier: Intended Audience :: System Administrators
Classifier: License :: OSI Approved :: MIT License
Classifier: Operating System :: MacOS
Classifier: Programming Language :: Python :: 3
Classifier: Programming Language :: Python :: 3.8
Classifier: Programming Language :: Python :: 3.9
Classifier: Programming Language :: Python :: 3.10
Classifier: Programming Language :: Python :: 3.11
Classifier: Programming Language :: Python :: 3.12
Classifier: Topic :: System :: Monitoring
Classifier: Topic :: System :: Hardware
Requires-Python: >=3.8
License-File: LICENSE
Requires-Dist: psutil<6.0.0,>=5.9.0
Requires-Dist: fastapi<1.0.0,>=0.104.0
Requires-Dist: uvicorn[standard]<1.0.0,>=0.24.0
Requires-Dist: websockets<13.0.0,>=12.0
Provides-Extra: dev
Requires-Dist: pytest>=7.0.0; extra == "dev"
Requires-Dist: black>=23.0.0; extra == "dev"
Requires-Dist: ruff>=0.1.0; extra == "dev"
Dynamic: license-file
